libgenrs/__init__.py
libgenrs/download.py
libgenrs/search.py
libgenrs/utils.py
tests/__init__.py
tests/libgen_test.py
libgenrs-0.2.3.dist-info/LICENSE
libgenrs-0.2.3.dist-info/METADATA
libgenrs-0.2.3.dist-info/WHEEL
libgenrs-0.2.3.dist-info/top_level.txt
libgenrs-0.2.3.dist-info/RECORD
