Metadata-Version: 2.2
Name: libgenrs
Version: 0.2.3
Summary: Asynchronous python lib for Libgen.rs
Home-page: https://github.com/ramanveerji/libgenrs
Download-URL: https://github.com/ramanveerji/libgenrs/archive/v0.2.3.tar.gz
License: MIT License
Classifier: Intended Audience :: Developers
Classifier: Operating System :: OS Independent
Classifier: Programming Language :: Python
Classifier: Programming Language :: Python :: 3.8
Classifier: Programming Language :: Python :: 3.9
Classifier: Topic :: Internet :: WWW/HTTP
License-File: LICENSE
Requires-Dist: aiofiles>=0.5.0
Requires-Dist: aiohttp>=3.6.0
Requires-Dist: beautifulsoup4>=4.9.0
Requires-Dist: lxml>=4.6.5
Requires-Dist: requests>=2.25.0
Requires-Dist: tldextract>=3.1.0
Dynamic: classifier
Dynamic: description
Dynamic: description-content-type
Dynamic: download-url
Dynamic: home-page
Dynamic: license
Dynamic: requires-dist
Dynamic: summary
